static_error_handler/__init__.py
static_error_handler/itertools.py
static_error_handler/py.typed
static_error_handler/static_error_handler.py
static_error_handler-0.1.5.dist-info/METADATA
static_error_handler-0.1.5.dist-info/WHEEL
static_error_handler-0.1.5.dist-info/licenses/LICENSE
static_error_handler-0.1.5.dist-info/RECORD
