Metadata-Version: 2.4
Name: static_error_handler
Version: 0.1.5
Summary: A minimal Python adaptation of Rust's Result type
Author: J-joon
License: MIT License
License-File: LICENSE
Classifier: License :: OSI Approved :: MIT License
Classifier: Operating System :: OS Independent
Classifier: Programming Language :: Python :: 3
Requires-Python: >=3.13
Provides-Extra: dev
Requires-Dist: coverage[toml]>=7.6; extra == 'dev'
Requires-Dist: mypy>=1.11; extra == 'dev'
Requires-Dist: pre-commit>=3.8; extra == 'dev'
Requires-Dist: pytest>=8.0; extra == 'dev'
Requires-Dist: ruff>=0.6; extra == 'dev'
